hotpot/__init__.py
hotpot/app.py
hotpot/exceptions.py
hotpot/globals.py
hotpot/sessions.py
hotpot/utils.py
hotpot/wrappers.py
hotpot-2.1.0.dist-info/LICENSE
hotpot-2.1.0.dist-info/METADATA
hotpot-2.1.0.dist-info/WHEEL
hotpot-2.1.0.dist-info/top_level.txt
hotpot-2.1.0.dist-info/RECORD
