Metadata-Version: 2.1
Name: hotpot
Version: 2.1.0
Summary: A tiny and easy python web framework just for your fun! :)
Home-page: https://github.com/RutaTang/Hotpot
Author: Ruta Tang
Author-email: 953259325@qq.com
License: UNKNOWN
Platform: UNKNOWN
Requires-Python: >=3.6
License-File: LICENSE
Requires-Dist: werkzeug
Requires-Dist: cryptography
Requires-Dist: pyjwt
